edit_distance.py
edit_distance-1.0.6.dist-info/LICENSE
edit_distance-1.0.6.dist-info/METADATA
edit_distance-1.0.6.dist-info/WHEEL
edit_distance-1.0.6.dist-info/entry_points.txt
edit_distance-1.0.6.dist-info/top_level.txt
edit_distance-1.0.6.dist-info/RECORD
