Metadata-Version: 2.1
Name: edit_distance
Version: 1.0.6
Summary: Computing edit distance on arbitrary Python sequences.
Home-page: https://github.com/belambert/editdistance
Author: Ben Lambert
Author-email: blambert@gmail.com
License: LICENSE.txt
Keywords: edit,distance,editdistance,levenshtein
Classifier: Development Status :: 5 - Production/Stable
Classifier: Environment :: Console
Classifier: Programming Language :: Python
Classifier: Topic :: Scientific/Engineering :: Artificial Intelligence
Classifier: Topic :: Text Processing
Classifier: Topic :: Utilities
Classifier: License :: OSI Approved :: Apache Software License
License-File: LICENSE
